expresstable/__init__.py
expresstable/cell.py
expresstable/exceptions.py
expresstable/row.py
expresstable/table.py
expresstable-0.1.1.dist-info/LICENSE
expresstable-0.1.1.dist-info/METADATA
expresstable-0.1.1.dist-info/WHEEL
expresstable-0.1.1.dist-info/top_level.txt
expresstable-0.1.1.dist-info/RECORD
