Metadata-Version: 2.1
Name: expresstable
Version: 0.1.1
Summary: Quickly create tables in Python
Home-page: https://github.com/christopherdavidsmith/expresstable
Author: Christopher Smith
Author-email: UNKNOWN
License: UNKNOWN
Platform: UNKNOWN
Classifier: Programming Language :: Python :: 3
Classifier: License :: OSI Approved :: MIT License
Classifier: Operating System :: OS Independent
Requires-Dist: termcolor (>=1.1.0)
